similarity/Sentence.py
similarity/Word.py
similarity/__init__.py
similarity/convert_score_and_distance_functions.py
similarity/find_most_similar.py
similarity/get_char_by_char_equality.py
similarity/get_sentence_similarity.py
similarity/get_similarity.py
similarity/get_string_similarity.py
similarity/jaro_winkler.py
similarity/levenshtein.py
similarity-0.0.1.dist-info/METADATA
similarity-0.0.1.dist-info/WHEEL
similarity-0.0.1.dist-info/top_level.txt
similarity-0.0.1.dist-info/RECORD
